{
  "Cases": [
    {
      "Input": [
        "4",
        "247",
        "588"
      ],
      "Output": "30381\n172578\n"
    },
    {
      "Input": [
        "4",
        "212",
        "117"
      ],
      "Output": "22366\n6786\n"
    },
    {
      "Input": [
        "4",
        "560",
        "548"
      ],
      "Output": "156520\n149878\n"
    },
    {
      "Input": [
        "4",
        "803",
        "875"
      ],
      "Output": "322003\n382375\n"
    },
    {
      "Input": [
        "4",
        "425",
        "694"
      ],
      "Output": "90100\n240471\n"
    },
    {
      "Input": [
        "4",
        "493",
        "445"
      ],
      "Output": "121278\n98790\n"
    },
    {
      "Input": [
        "4",
        "40",
        "407"
      ],
      "Output": "780\n82621\n"
    },
    {
      "Input": [
        "4",
        "146",
        "524"
      ],
      "Output": "10585\n137026\n"
    },
    {
      "Input": [
        "4",
        "258",
        "165"
      ],
      "Output": "33153\n13530\n"
    },
    {
      "Input": [
        "4",
        "252",
        "322"
      ],
      "Output": "31626\n51681\n"
    },
    {
      "Input": [
        "4",
        "15",
        "390"
      ],
      "Output": "105\n75855\n"
    },
    {
      "Input": [
        "4",
        "281",
        "409"
      ],
      "Output": "39340\n83436\n"
    },
    {
      "Input": [
        "4",
        "689",
        "39"
      ],
      "Output": "237016\n741\n"
    },
    {
      "Input": [
        "4",
        "838",
        "706"
      ],
      "Output": "350703\n248865\n"
    },
    {
      "Input": [
        "4",
        "833",
        "385"
      ],
      "Output": "346528\n73920\n"
    },
    {
      "Input": [
        "4",
        "982",
        "223"
      ],
      "Output": "481671\n24753\n"
    },
    {
      "Input": [
        "4",
        "346",
        "892"
      ],
      "Output": "59685\n397386\n"
    },
    {
      "Input": [
        "4",
        "228",
        "306"
      ],
      "Output": "25878\n46665\n"
    },
    {
      "Input": [
        "4",
        "645",
        "911"
      ],
      "Output": "207690\n414505\n"
    },
    {
      "Input": [
        "4",
        "249",
        "557"
      ],
      "Output": "30876\n154846\n"
    },
    {
      "Input": [
        "4",
        "330",
        "784"
      ],
      "Output": "54285\n306936\n"
    },
    {
      "Input": [
        "4",
        "57",
        "447"
      ],
      "Output": "1596\n99681\n"
    },
    {
      "Input": [
        "4",
        "503",
        "900"
      ],
      "Output": "126253\n404550\n"
    },
    {
      "Input": [
        "4",
        "88",
        "917"
      ],
      "Output": "3828\n419986\n"
    },
    {
      "Input": [
        "4",
        "638",
        "493"
      ],
      "Output": "203203\n121278\n"
    },
    {
      "Input": [
        "4",
        "502",
        "627"
      ],
      "Output": "125751\n196251\n"
    },
    {
      "Input": [
        "4",
        "949",
        "308"
      ],
      "Output": "449826\n47278\n"
    },
    {
      "Input": [
        "4",
        "267",
        "975"
      ],
      "Output": "35511\n474825\n"
    },
    {
      "Input": [
        "4",
        "771",
        "473"
      ],
      "Output": "296835\n111628\n"
    },
    {
      "Input": [
        "4",
        "984",
        "337"
      ],
      "Output": "483636\n56616\n"
    },
    {
      "Input": [
        "4",
        "191",
        "999"
      ],
      "Output": "18145\n498501\n"
    },
    {
      "Input": [
        "4",
        "832",
        "80"
      ],
      "Output": "345696\n3160\n"
    },
    {
      "Input": [
        "4",
        "251",
        "730"
      ],
      "Output": "31375\n266085\n"
    },
    {
      "Input": [
        "4",
        "555",
        "855"
      ],
      "Output": "153735\n365085\n"
    },
    {
      "Input": [
        "4",
        "956",
        "514"
      ],
      "Output": "456490\n131841\n"
    },
    {
      "Input": [
        "4",
        "278",
        "824"
      ],
      "Output": "38503\n339076\n"
    },
    {
      "Input": [
        "4",
        "901",
        "599"
      ],
      "Output": "405450\n179101\n"
    },
    {
      "Input": [
        "4",
        "905",
        "73"
      ],
      "Output": "409060\n2628\n"
    },
    {
      "Input": [
        "4",
        "957",
        "24"
      ],
      "Output": "457446\n276\n"
    },
    {
      "Input": [
        "4",
        "251",
        "912"
      ],
      "Output": "31375\n415416\n"
    },
    {
      "Input": [
        "4",
        "105",
        "458"
      ],
      "Output": "5460\n104653\n"
    },
    {
      "Input": [
        "4",
        "435",
        "185"
      ],
      "Output": "94395\n17020\n"
    },
    {
      "Input": [
        "4",
        "406",
        "920"
      ],
      "Output": "82215\n422740\n"
    },
    {
      "Input": [
        "4",
        "556",
        "919"
      ],
      "Output": "154290\n421821\n"
    },
    {
      "Input": [
        "4",
        "825",
        "612"
      ],
      "Output": "339900\n186966\n"
    },
    {
      "Input": [
        "4",
        "674",
        "327"
      ],
      "Output": "226801\n53301\n"
    },
    {
      "Input": [
        "4",
        "401",
        "772"
      ],
      "Output": "80200\n297606\n"
    },
    {
      "Input": [
        "4",
        "16",
        "117"
      ],
      "Output": "120\n6786\n"
    },
    {
      "Input": [
        "4",
        "133",
        "56"
      ],
      "Output": "8778\n1540\n"
    },
    {
      "Input": [
        "4",
        "987",
        "882"
      ],
      "Output": "486591\n388521\n"
    },
    {
      "Input": [
        "4",
        "113",
        "234"
      ],
      "Output": "6328\n27261\n"
    },
    {
      "Input": [
        "4",
        "831",
        "461"
      ],
      "Output": "344865\n106030\n"
    },
    {
      "Input": [
        "4",
        "635",
        "813"
      ],
      "Output": "201295\n330078\n"
    },
    {
      "Input": [
        "4",
        "900",
        "181"
      ],
      "Output": "404550\n16290\n"
    },
    {
      "Input": [
        "4",
        "325",
        "548"
      ],
      "Output": "52650\n149878\n"
    },
    {
      "Input": [
        "4",
        "1",
        "566"
      ],
      "Output": "0\n159895\n"
    },
    {
      "Input": [
        "4",
        "648",
        "402"
      ],
      "Output": "209628\n80601\n"
    },
    {
      "Input": [
        "4",
        "17",
        "113"
      ],
      "Output": "136\n6328\n"
    },
    {
      "Input": [
        "4",
        "669",
        "237"
      ],
      "Output": "223446\n27966\n"
    },
    {
      "Input": [
        "4",
        "508",
        "662"
      ],
      "Output": "128778\n218791\n"
    },
    {
      "Input": [
        "4",
        "1000",
        "567"
      ],
      "Output": "499500\n160461\n"
    },
    {
      "Input": [
        "4",
        "214",
        "982"
      ],
      "Output": "22791\n481671\n"
    },
    {
      "Input": [
        "4",
        "384",
        "840"
      ],
      "Output": "73536\n352380\n"
    },
    {
      "Input": [
        "4",
        "284",
        "898"
      ],
      "Output": "40186\n402753\n"
    },
    {
      "Input": [
        "4",
        "309",
        "467"
      ],
      "Output": "47586\n108811\n"
    },
    {
      "Input": [
        "4",
        "817",
        "258"
      ],
      "Output": "333336\n33153\n"
    },
    {
      "Input": [
        "4",
        "66",
        "37"
      ],
      "Output": "2145\n666\n"
    },
    {
      "Input": [
        "4",
        "575",
        "945"
      ],
      "Output": "165025\n446040\n"
    },
    {
      "Input": [
        "4",
        "585",
        "469"
      ],
      "Output": "170820\n109746\n"
    },
    {
      "Input": [
        "4",
        "244",
        "325"
      ],
      "Output": "29646\n52650\n"
    },
    {
      "Input": [
        "4",
        "538",
        "90"
      ],
      "Output": "144453\n4005\n"
    },
    {
      "Input": [
        "4",
        "774",
        "534"
      ],
      "Output": "299151\n142311\n"
    },
    {
      "Input": [
        "4",
        "177",
        "928"
      ],
      "Output": "15576\n430128\n"
    },
    {
      "Input": [
        "4",
        "832",
        "463"
      ],
      "Output": "345696\n106953\n"
    },
    {
      "Input": [
        "4",
        "938",
        "684"
      ],
      "Output": "439453\n233586\n"
    },
    {
      "Input": [
        "4",
        "247",
        "98"
      ],
      "Output": "30381\n4753\n"
    },
    {
      "Input": [
        "4",
        "737",
        "120"
      ],
      "Output": "271216\n7140\n"
    },
    {
      "Input": [
        "4",
        "73",
        "351"
      ],
      "Output": "2628\n61425\n"
    },
    {
      "Input": [
        "4",
        "443",
        "862"
      ],
      "Output": "97903\n371091\n"
    },
    {
      "Input": [
        "4",
        "845",
        "525"
      ],
      "Output": "356590\n137550\n"
    },
    {
      "Input": [
        "4",
        "962",
        "459"
      ],
      "Output": "462241\n105111\n"
    },
    {
      "Input": [
        "4",
        "593",
        "626"
      ],
      "Output": "175528\n195625\n"
    },
    {
      "Input": [
        "4",
        "340",
        "575"
      ],
      "Output": "57630\n165025\n"
    },
    {
      "Input": [
        "4",
        "234",
        "981"
      ],
      "Output": "27261\n480690\n"
    },
    {
      "Input": [
        "4",
        "167",
        "161"
      ],
      "Output": "13861\n12880\n"
    },
    {
      "Input": [
        "4",
        "782",
        "675"
      ],
      "Output": "305371\n227475\n"
    },
    {
      "Input": [
        "4",
        "978",
        "171"
      ],
      "Output": "477753\n14535\n"
    },
    {
      "Input": [
        "4",
        "650",
        "871"
      ],
      "Output": "210925\n378885\n"
    },
    {
      "Input": [
        "4",
        "826",
        "368"
      ],
      "Output": "340725\n67528\n"
    },
    {
      "Input": [
        "4",
        "444",
        "752"
      ],
      "Output": "98346\n282376\n"
    },
    {
      "Input": [
        "4",
        "760",
        "751"
      ],
      "Output": "288420\n281625\n"
    },
    {
      "Input": [
        "4",
        "496",
        "147"
      ],
      "Output": "122760\n10731\n"
    },
    {
      "Input": [
        "4",
        "930",
        "413"
      ],
      "Output": "431985\n85078\n"
    },
    {
      "Input": [
        "4",
        "367",
        "376"
      ],
      "Output": "67161\n70500\n"
    },
    {
      "Input": [
        "4",
        "250",
        "906"
      ],
      "Output": "31125\n409965\n"
    },
    {
      "Input": [
        "4",
        "566",
        "244"
      ],
      "Output": "159895\n29646\n"
    },
    {
      "Input": [
        "4",
        "153",
        "663"
      ],
      "Output": "11628\n219453\n"
    },
    {
      "Input": [
        "4",
        "511",
        "846"
      ],
      "Output": "130305\n357435\n"
    },
    {
      "Input": [
        "4",
        "819",
        "86"
      ],
      "Output": "334971\n3655\n"
    },
    {
      "Input": [
        "4",
        "132",
        "690"
      ],
      "Output": "8646\n237705\n"
    },
    {
      "Input": [
        "4",
        "464",
        "801"
      ],
      "Output": "107416\n320400\n"
    },
    {
      "Input": [
        "4",
        "873",
        "264"
      ],
      "Output": "380628\n34716\n"
    },
    {
      "Input": [
        "4",
        "577",
        "3"
      ],
      "Output": "166176\n3\n"
    },
    {
      "Input": [
        "4",
        "897",
        "621"
      ],
      "Output": "401856\n192510\n"
    },
    {
      "Input": [
        "4",
        "804",
        "339"
      ],
      "Output": "322806\n57291\n"
    },
    {
      "Input": [
        "4",
        "234",
        "360"
      ],
      "Output": "27261\n64620\n"
    },
    {
      "Input": [
        "4",
        "982",
        "534"
      ],
      "Output": "481671\n142311\n"
    },
    {
      "Input": [
        "4",
        "540",
        "378"
      ],
      "Output": "145530\n71253\n"
    },
    {
      "Input": [
        "4",
        "927",
        "502"
      ],
      "Output": "429201\n125751\n"
    },
    {
      "Input": [
        "4",
        "792",
        "803"
      ],
      "Output": "313236\n322003\n"
    },
    {
      "Input": [
        "4",
        "926",
        "91"
      ],
      "Output": "428275\n4095\n"
    },
    {
      "Input": [
        "4",
        "512",
        "587"
      ],
      "Output": "130816\n171991\n"
    },
    {
      "Input": [
        "4",
        "604",
        "547"
      ],
      "Output": "182106\n149331\n"
    },
    {
      "Input": [
        "4",
        "23",
        "710"
      ],
      "Output": "253\n251695\n"
    },
    {
      "Input": [
        "4",
        "377",
        "647"
      ],
      "Output": "70876\n208981\n"
    },
    {
      "Input": [
        "4",
        "470",
        "476"
      ],
      "Output": "110215\n113050\n"
    },
    {
      "Input": [
        "4",
        "142",
        "574"
      ],
      "Output": "10011\n164451\n"
    },
    {
      "Input": [
        "4",
        "522",
        "11"
      ],
      "Output": "135981\n55\n"
    },
    {
      "Input": [
        "4",
        "401",
        "873"
      ],
      "Output": "80200\n380628\n"
    },
    {
      "Input": [
        "4",
        "128",
        "65"
      ],
      "Output": "8128\n2080\n"
    },
    {
      "Input": [
        "4",
        "976",
        "695"
      ],
      "Output": "475800\n241165\n"
    },
    {
      "Input": [
        "4",
        "831",
        "328"
      ],
      "Output": "344865\n53628\n"
    },
    {
      "Input": [
        "4",
        "643",
        "744"
      ],
      "Output": "206403\n276396\n"
    },
    {
      "Input": [
        "4",
        "687",
        "874"
      ],
      "Output": "235641\n381501\n"
    },
    {
      "Input": [
        "4",
        "852",
        "519"
      ],
      "Output": "362526\n134421\n"
    },
    {
      "Input": [
        "4",
        "744",
        "171"
      ],
      "Output": "276396\n14535\n"
    },
    {
      "Input": [
        "4",
        "507",
        "483"
      ],
      "Output": "128271\n116403\n"
    },
    {
      "Input": [
        "4",
        "291",
        "559"
      ],
      "Output": "42195\n155961\n"
    },
    {
      "Input": [
        "4",
        "308",
        "950"
      ],
      "Output": "47278\n450775\n"
    },
    {
      "Input": [
        "4",
        "207",
        "94"
      ],
      "Output": "21321\n4371\n"
    },
    {
      "Input": [
        "4",
        "554",
        "102"
      ],
      "Output": "153181\n5151\n"
    },
    {
      "Input": [
        "4",
        "881",
        "760"
      ],
      "Output": "387640\n288420\n"
    },
    {
      "Input": [
        "4",
        "979",
        "955"
      ],
      "Output": "478731\n455535\n"
    },
    {
      "Input": [
        "4",
        "731",
        "225"
      ],
      "Output": "266815\n25200\n"
    },
    {
      "Input": [
        "4",
        "617",
        "590"
      ],
      "Output": "190036\n173755\n"
    },
    {
      "Input": [
        "4",
        "955",
        "21"
      ],
      "Output": "455535\n210\n"
    },
    {
      "Input": [
        "4",
        "618",
        "253"
      ],
      "Output": "190653\n31878\n"
    },
    {
      "Input": [
        "4",
        "959",
        "454"
      ],
      "Output": "459361\n102831\n"
    },
    {
      "Input": [
        "4",
        "228",
        "263"
      ],
      "Output": "25878\n34453\n"
    },
    {
      "Input": [
        "4",
        "427",
        "596"
      ],
      "Output": "90951\n177310\n"
    },
    {
      "Input": [
        "4",
        "763",
        "453"
      ],
      "Output": "290703\n102378\n"
    },
    {
      "Input": [
        "4",
        "753",
        "466"
      ],
      "Output": "283128\n108345\n"
    },
    {
      "Input": [
        "4",
        "626",
        "800"
      ],
      "Output": "195625\n319600\n"
    },
    {
      "Input": [
        "4",
        "180",
        "430"
      ],
      "Output": "16110\n92235\n"
    },
    {
      "Input": [
        "4",
        "639",
        "917"
      ],
      "Output": "203841\n419986\n"
    },
    {
      "Input": [
        "4",
        "515",
        "102"
      ],
      "Output": "132355\n5151\n"
    },
    {
      "Input": [
        "4",
        "44",
        "525"
      ],
      "Output": "946\n137550\n"
    },
    {
      "Input": [
        "4",
        "686",
        "333"
      ],
      "Output": "234955\n55278\n"
    },
    {
      "Input": [
        "4",
        "604",
        "962"
      ],
      "Output": "182106\n462241\n"
    },
    {
      "Input": [
        "4",
        "509",
        "775"
      ],
      "Output": "129286\n299925\n"
    },
    {
      "Input": [
        "4",
        "551",
        "774"
      ],
      "Output": "151525\n299151\n"
    },
    {
      "Input": [
        "4",
        "690",
        "924"
      ],
      "Output": "237705\n426426\n"
    },
    {
      "Input": [
        "4",
        "794",
        "905"
      ],
      "Output": "314821\n409060\n"
    },
    {
      "Input": [
        "4",
        "653",
        "788"
      ],
      "Output": "212878\n310078\n"
    },
    {
      "Input": [
        "4",
        "553",
        "329"
      ],
      "Output": "152628\n53956\n"
    },
    {
      "Input": [
        "4",
        "153",
        "411"
      ],
      "Output": "11628\n84255\n"
    },
    {
      "Input": [
        "4",
        "695",
        "662"
      ],
      "Output": "241165\n218791\n"
    },
    {
      "Input": [
        "4",
        "615",
        "559"
      ],
      "Output": "188805\n155961\n"
    },
    {
      "Input": [
        "4",
        "62",
        "169"
      ],
      "Output": "1891\n14196\n"
    },
    {
      "Input": [
        "4",
        "924",
        "630"
      ],
      "Output": "426426\n198135\n"
    },
    {
      "Input": [
        "4",
        "655",
        "919"
      ],
      "Output": "214185\n421821\n"
    },
    {
      "Input": [
        "4",
        "224",
        "78"
      ],
      "Output": "24976\n3003\n"
    },
    {
      "Input": [
        "4",
        "762",
        "381"
      ],
      "Output": "289941\n72390\n"
    },
    {
      "Input": [
        "4",
        "762",
        "463"
      ],
      "Output": "289941\n106953\n"
    },
    {
      "Input": [
        "4",
        "870",
        "108"
      ],
      "Output": "378015\n5778\n"
    },
    {
      "Input": [
        "4",
        "733",
        "714"
      ],
      "Output": "268278\n254541\n"
    },
    {
      "Input": [
        "4",
        "992",
        "427"
      ],
      "Output": "491536\n90951\n"
    },
    {
      "Input": [
        "4",
        "607",
        "745"
      ],
      "Output": "183921\n277140\n"
    },
    {
      "Input": [
        "4",
        "290",
        "277"
      ],
      "Output": "41905\n38226\n"
    },
    {
      "Input": [
        "4",
        "903",
        "819"
      ],
      "Output": "407253\n334971\n"
    },
    {
      "Input": [
        "4",
        "311",
        "120"
      ],
      "Output": "48205\n7140\n"
    },
    {
      "Input": [
        "4",
        "40",
        "599"
      ],
      "Output": "780\n179101\n"
    },
    {
      "Input": [
        "4",
        "405",
        "900"
      ],
      "Output": "81810\n404550\n"
    },
    {
      "Input": [
        "4",
        "821",
        "163"
      ],
      "Output": "336610\n13203\n"
    },
    {
      "Input": [
        "4",
        "473",
        "309"
      ],
      "Output": "111628\n47586\n"
    },
    {
      "Input": [
        "4",
        "575",
        "84"
      ],
      "Output": "165025\n3486\n"
    },
    {
      "Input": [
        "4",
        "347",
        "518"
      ],
      "Output": "60031\n133903\n"
    },
    {
      "Input": [
        "4",
        "536",
        "462"
      ],
      "Output": "143380\n106491\n"
    },
    {
      "Input": [
        "4",
        "873",
        "142"
      ],
      "Output": "380628\n10011\n"
    },
    {
      "Input": [
        "4",
        "862",
        "279"
      ],
      "Output": "371091\n38781\n"
    },
    {
      "Input": [
        "4",
        "238",
        "428"
      ],
      "Output": "28203\n91378\n"
    },
    {
      "Input": [
        "4",
        "483",
        "858"
      ],
      "Output": "116403\n367653\n"
    },
    {
      "Input": [
        "4",
        "850",
        "959"
      ],
      "Output": "360825\n459361\n"
    },
    {
      "Input": [
        "4",
        "291",
        "782"
      ],
      "Output": "42195\n305371\n"
    },
    {
      "Input": [
        "4",
        "530",
        "860"
      ],
      "Output": "140185\n369370\n"
    },
    {
      "Input": [
        "4",
        "14",
        "606"
      ],
      "Output": "91\n183315\n"
    },
    {
      "Input": [
        "4",
        "698",
        "627"
      ],
      "Output": "243253\n196251\n"
    },
    {
      "Input": [
        "4",
        "928",
        "14"
      ],
      "Output": "430128\n91\n"
    },
    {
      "Input": [
        "4",
        "898",
        "22"
      ],
      "Output": "402753\n231\n"
    },
    {
      "Input": [
        "4",
        "92",
        "716"
      ],
      "Output": "4186\n255970\n"
    },
    {
      "Input": [
        "4",
        "628",
        "152"
      ],
      "Output": "196878\n11476\n"
    },
    {
      "Input": [
        "4",
        "716",
        "392"
      ],
      "Output": "255970\n76636\n"
    },
    {
      "Input": [
        "4",
        "164",
        "752"
      ],
      "Output": "13366\n282376\n"
    },
    {
      "Input": [
        "4",
        "283",
        "239"
      ],
      "Output": "39903\n28441\n"
    },
    {
      "Input": [
        "4",
        "89",
        "758"
      ],
      "Output": "3916\n286903\n"
    },
    {
      "Input": [
        "4",
        "243",
        "26"
      ],
      "Output": "29403\n325\n"
    },
    {
      "Input": [
        "4",
        "919",
        "864"
      ],
      "Output": "421821\n372816\n"
    },
    {
      "Input": [
        "4",
        "218",
        "155"
      ],
      "Output": "23653\n11935\n"
    },
    {
      "Input": [
        "4",
        "972",
        "994"
      ],
      "Output": "471906\n493521\n"
    },
    {
      "Input": [
        "4",
        "159",
        "172"
      ],
      "Output": "12561\n14706\n"
    },
    {
      "Input": [
        "4",
        "599",
        "717"
      ],
      "Output": "179101\n256686\n"
    },
    {
      "Input": [
        "4",
        "13",
        "32"
      ],
      "Output": "78\n496\n"
    },
    {
      "Input": [
        "4",
        "348",
        "163"
      ],
      "Output": "60378\n13203\n"
    },
    {
      "Input": [
        "4",
        "56",
        "833"
      ],
      "Output": "1540\n346528\n"
    },
    {
      "Input": [
        "4",
        "146",
        "631"
      ],
      "Output": "10585\n198765\n"
    },
    {
      "Input": [
        "4",
        "310",
        "459"
      ],
      "Output": "47895\n105111\n"
    },
    {
      "Input": [
        "4",
        "320",
        "222"
      ],
      "Output": "51040\n24531\n"
    },
    {
      "Input": [
        "4",
        "408",
        "413"
      ],
      "Output": "83028\n85078\n"
    },
    {
      "Input": [
        "4",
        "355",
        "506"
      ],
      "Output": "62835\n127765\n"
    },
    {
      "Input": [
        "4",
        "423",
        "183"
      ],
      "Output": "89253\n16653\n"
    },
    {
      "Input": [
        "4",
        "481",
        "352"
      ],
      "Output": "115440\n61776\n"
    },
    {
      "Input": [
        "4",
        "423",
        "285"
      ],
      "Output": "89253\n40470\n"
    },
    {
      "Input": [
        "4",
        "842",
        "378"
      ],
      "Output": "354061\n71253\n"
    },
    {
      "Input": [
        "4",
        "87",
        "343"
      ],
      "Output": "3741\n58653\n"
    },
    {
      "Input": [
        "4",
        "107",
        "346"
      ],
      "Output": "5671\n59685\n"
    },
    {
      "Input": [
        "4",
        "792",
        "676"
      ],
      "Output": "313236\n228150\n"
    },
    {
      "Input": [
        "4",
        "271",
        "811"
      ],
      "Output": "36585\n328455\n"
    },
    {
      "Input": [
        "4",
        "244",
        "663"
      ],
      "Output": "29646\n219453\n"
    },
    {
      "Input": [
        "4",
        "611",
        "642"
      ],
      "Output": "186355\n205761\n"
    },
    {
      "Input": [
        "4",
        "109",
        "110"
      ],
      "Output": "5886\n5995\n"
    },
    {
      "Input": [
        "4",
        "307",
        "243"
      ],
      "Output": "46971\n29403\n"
    },
    {
      "Input": [
        "4",
        "977",
        "949"
      ],
      "Output": "476776\n449826\n"
    },
    {
      "Input": [
        "4",
        "932",
        "886"
      ],
      "Output": "433846\n392055\n"
    },
    {
      "Input": [
        "4",
        "796",
        "87"
      ],
      "Output": "316410\n3741\n"
    },
    {
      "Input": [
        "4",
        "855",
        "69"
      ],
      "Output": "365085\n2346\n"
    },
    {
      "Input": [
        "4",
        "75",
        "229"
      ],
      "Output": "2775\n26106\n"
    },
    {
      "Input": [
        "4",
        "578",
        "78"
      ],
      "Output": "166753\n3003\n"
    },
    {
      "Input": [
        "4",
        "562",
        "699"
      ],
      "Output": "157641\n243951\n"
    },
    {
      "Input": [
        "4",
        "277",
        "375"
      ],
      "Output": "38226\n70125\n"
    },
    {
      "Input": [
        "4",
        "601",
        "571"
      ],
      "Output": "180300\n162735\n"
    },
    {
      "Input": [
        "4",
        "742",
        "948"
      ],
      "Output": "274911\n448878\n"
    },
    {
      "Input": [
        "4",
        "961",
        "10"
      ],
      "Output": "461280\n45\n"
    },
    {
      "Input": [
        "4",
        "203",
        "969"
      ],
      "Output": "20503\n468996\n"
    },
    {
      "Input": [
        "4",
        "790",
        "88"
      ],
      "Output": "311655\n3828\n"
    },
    {
      "Input": [
        "4",
        "458",
        "772"
      ],
      "Output": "104653\n297606\n"
    },
    {
      "Input": [
        "4",
        "646",
        "673"
      ],
      "Output": "208335\n226128\n"
    },
    {
      "Input": [
        "4",
        "220",
        "105"
      ],
      "Output": "24090\n5460\n"
    },
    {
      "Input": [
        "4",
        "16",
        "216"
      ],
      "Output": "120\n23220\n"
    },
    {
      "Input": [
        "4",
        "734",
        "957"
      ],
      "Output": "269011\n457446\n"
    },
    {
      "Input": [
        "4",
        "406",
        "775"
      ],
      "Output": "82215\n299925\n"
    },
    {
      "Input": [
        "4",
        "332",
        "729"
      ],
      "Output": "54946\n265356\n"
    },
    {
      "Input": [
        "4",
        "264",
        "292"
      ],
      "Output": "34716\n42486\n"
    },
    {
      "Input": [
        "4",
        "703",
        "193"
      ],
      "Output": "246753\n18528\n"
    },
    {
      "Input": [
        "4",
        "811",
        "835"
      ],
      "Output": "328455\n348195\n"
    },
    {
      "Input": [
        "4",
        "562",
        "900"
      ],
      "Output": "157641\n404550\n"
    },
    {
      "Input": [
        "4",
        "191",
        "268"
      ],
      "Output": "18145\n35778\n"
    },
    {
      "Input": [
        "4",
        "117",
        "841"
      ],
      "Output": "6786\n353220\n"
    },
    {
      "Input": [
        "4",
        "763",
        "883"
      ],
      "Output": "290703\n389403\n"
    },
    {
      "Input": [
        "4",
        "450",
        "912"
      ],
      "Output": "101025\n415416\n"
    },
    {
      "Input": [
        "4",
        "603",
        "312"
      ],
      "Output": "181503\n48516\n"
    },
    {
      "Input": [
        "4",
        "424",
        "725"
      ],
      "Output": "89676\n262450\n"
    },
    {
      "Input": [
        "4",
        "749",
        "812"
      ],
      "Output": "280126\n329266\n"
    },
    {
      "Input": [
        "4",
        "785",
        "430"
      ],
      "Output": "307720\n92235\n"
    },
    {
      "Input": [
        "4",
        "51",
        "541"
      ],
      "Output": "1275\n146070\n"
    },
    {
      "Input": [
        "4",
        "259",
        "920"
      ],
      "Output": "33411\n422740\n"
    },
    {
      "Input": [
        "4",
        "967",
        "255"
      ],
      "Output": "467061\n32385\n"
    },
    {
      "Input": [
        "4",
        "969",
        "487"
      ],
      "Output": "468996\n118341\n"
    },
    {
      "Input": [
        "4",
        "891",
        "847"
      ],
      "Output": "396495\n358281\n"
    },
    {
      "Input": [
        "4",
        "531",
        "794"
      ],
      "Output": "140715\n314821\n"
    },
    {
      "Input": [
        "4",
        "213",
        "171"
      ],
      "Output": "22578\n14535\n"
    },
    {
      "Input": [
        "4",
        "877",
        "711"
      ],
      "Output": "384126\n252405\n"
    },
    {
      "Input": [
        "4",
        "206",
        "584"
      ],
      "Output": "21115\n170236\n"
    },
    {
      "Input": [
        "4",
        "860",
        "447"
      ],
      "Output": "369370\n99681\n"
    },
    {
      "Input": [
        "4",
        "1",
        "613"
      ],
      "Output": "0\n187578\n"
    },
    {
      "Input": [
        "4",
        "670",
        "798"
      ],
      "Output": "224115\n318003\n"
    },
    {
      "Input": [
        "4",
        "410",
        "305"
      ],
      "Output": "83845\n46360\n"
    },
    {
      "Input": [
        "4",
        "409",
        "420"
      ],
      "Output": "83436\n87990\n"
    },
    {
      "Input": [
        "4",
        "116",
        "626"
      ],
      "Output": "6670\n195625\n"
    },
    {
      "Input": [
        "4",
        "48",
        "825"
      ],
      "Output": "1128\n339900\n"
    },
    {
      "Input": [
        "4",
        "18",
        "607"
      ],
      "Output": "153\n183921\n"
    },
    {
      "Input": [
        "4",
        "558",
        "961"
      ],
      "Output": "155403\n461280\n"
    },
    {
      "Input": [
        "4",
        "829",
        "290"
      ],
      "Output": "343206\n41905\n"
    },
    {
      "Input": [
        "4",
        "99",
        "811"
      ],
      "Output": "4851\n328455\n"
    },
    {
      "Input": [
        "4",
        "978",
        "117"
      ],
      "Output": "477753\n6786\n"
    },
    {
      "Input": [
        "4",
        "669",
        "235"
      ],
      "Output": "223446\n27495\n"
    },
    {
      "Input": [
        "4",
        "893",
        "266"
      ],
      "Output": "398278\n35245\n"
    },
    {
      "Input": [
        "4",
        "261",
        "696"
      ],
      "Output": "33930\n241860\n"
    },
    {
      "Input": [
        "4",
        "100",
        "852"
      ],
      "Output": "4950\n362526\n"
    },
    {
      "Input": [
        "4",
        "461",
        "667"
      ],
      "Output": "106030\n222111\n"
    },
    {
      "Input": [
        "4",
        "659",
        "82"
      ],
      "Output": "216811\n3321\n"
    },
    {
      "Input": [
        "4",
        "152",
        "713"
      ],
      "Output": "11476\n253828\n"
    },
    {
      "Input": [
        "4",
        "276",
        "831"
      ],
      "Output": "37950\n344865\n"
    },
    {
      "Input": [
        "4",
        "114",
        "760"
      ],
      "Output": "6441\n288420\n"
    },
    {
      "Input": [
        "4",
        "526",
        "396"
      ],
      "Output": "138075\n78210\n"
    },
    {
      "Input": [
        "4",
        "348",
        "189"
      ],
      "Output": "60378\n17766\n"
    },
    {
      "Input": [
        "4",
        "846",
        "665"
      ],
      "Output": "357435\n220780\n"
    },
    {
      "Input": [
        "4",
        "947",
        "160"
      ],
      "Output": "447931\n12720\n"
    },
    {
      "Input": [
        "4",
        "716",
        "915"
      ],
      "Output": "255970\n418155\n"
    },
    {
      "Input": [
        "4",
        "417",
        "842"
      ],
      "Output": "86736\n354061\n"
    },
    {
      "Input": [
        "4",
        "229",
        "898"
      ],
      "Output": "26106\n402753\n"
    },
    {
      "Input": [
        "4",
        "237",
        "887"
      ],
      "Output": "27966\n392941\n"
    },
    {
      "Input": [
        "4",
        "950",
        "163"
      ],
      "Output": "450775\n13203\n"
    },
    {
      "Input": [
        "4",
        "622",
        "771"
      ],
      "Output": "193131\n296835\n"
    },
    {
      "Input": [
        "4",
        "1",
        "949"
      ],
      "Output": "0\n449826\n"
    },
    {
      "Input": [
        "4",
        "784",
        "791"
      ],
      "Output": "306936\n312445\n"
    },
    {
      "Input": [
        "4",
        "142",
        "227"
      ],
      "Output": "10011\n25651\n"
    },
    {
      "Input": [
        "4",
        "854",
        "892"
      ],
      "Output": "364231\n397386\n"
    },
    {
      "Input": [
        "4",
        "110",
        "409"
      ],
      "Output": "5995\n83436\n"
    },
    {
      "Input": [
        "4",
        "940",
        "616"
      ],
      "Output": "441330\n189420\n"
    },
    {
      "Input": [
        "4",
        "127",
        "486"
      ],
      "Output": "8001\n117855\n"
    },
    {
      "Input": [
        "4",
        "236",
        "738"
      ],
      "Output": "27730\n271953\n"
    },
    {
      "Input": [
        "4",
        "376",
        "187"
      ],
      "Output": "70500\n17391\n"
    },
    {
      "Input": [
        "4",
        "103",
        "210"
      ],
      "Output": "5253\n21945\n"
    },
    {
      "Input": [
        "4",
        "639",
        "334"
      ],
      "Output": "203841\n55611\n"
    },
    {
      "Input": [
        "4",
        "485",
        "621"
      ],
      "Output": "117370\n192510\n"
    },
    {
      "Input": [
        "4",
        "945",
        "35"
      ],
      "Output": "446040\n595\n"
    },
    {
      "Input": [
        "4",
        "428",
        "875"
      ],
      "Output": "91378\n382375\n"
    },
    {
      "Input": [
        "4",
        "756",
        "626"
      ],
      "Output": "285390\n195625\n"
    },
    {
      "Input": [
        "4",
        "366",
        "261"
      ],
      "Output": "66795\n33930\n"
    },
    {
      "Input": [
        "4",
        "315",
        "959"
      ],
      "Output": "49455\n459361\n"
    },
    {
      "Input": [
        "4",
        "183",
        "897"
      ],
      "Output": "16653\n401856\n"
    },
    {
      "Input": [
        "4",
        "80",
        "956"
      ],
      "Output": "3160\n456490\n"
    },
    {
      "Input": [
        "4",
        "703",
        "968"
      ],
      "Output": "246753\n468028\n"
    },
    {
      "Input": [
        "4",
        "25",
        "857"
      ],
      "Output": "300\n366796\n"
    },
    {
      "Input": [
        "4",
        "338",
        "413"
      ],
      "Output": "56953\n85078\n"
    },
    {
      "Input": [
        "4",
        "994",
        "618"
      ],
      "Output": "493521\n190653\n"
    },
    {
      "Input": [
        "4",
        "955",
        "793"
      ],
      "Output": "455535\n314028\n"
    },
    {
      "Input": [
        "4",
        "22",
        "968"
      ],
      "Output": "231\n468028\n"
    },
    {
      "Input": [
        "4",
        "606",
        "897"
      ],
      "Output": "183315\n401856\n"
    },
    {
      "Input": [
        "4",
        "761",
        "634"
      ],
      "Output": "289180\n200661\n"
    },
    {
      "Input": [
        "4",
        "17",
        "747"
      ],
      "Output": "136\n278631\n"
    },
    {
      "Input": [
        "4",
        "432",
        "252"
      ],
      "Output": "93096\n31626\n"
    },
    {
      "Input": [
        "4",
        "556",
        "134"
      ],
      "Output": "154290\n8911\n"
    },
    {
      "Input": [
        "4",
        "982",
        "856"
      ],
      "Output": "481671\n365940\n"
    },
    {
      "Input": [
        "4",
        "444",
        "953"
      ],
      "Output": "98346\n453628\n"
    },
    {
      "Input": [
        "4",
        "41",
        "703"
      ],
      "Output": "820\n246753\n"
    },
    {
      "Input": [
        "4",
        "490",
        "506"
      ],
      "Output": "119805\n127765\n"
    },
    {
      "Input": [
        "4",
        "671",
        "335"
      ],
      "Output": "224785\n55945\n"
    },
    {
      "Input": [
        "4",
        "277",
        "553"
      ],
      "Output": "38226\n152628\n"
    },
    {
      "Input": [
        "4",
        "691",
        "524"
      ],
      "Output": "238395\n137026\n"
    },
    {
      "Input": [
        "4",
        "148",
        "374"
      ],
      "Output": "10878\n69751\n"
    },
    {
      "Input": [
        "4",
        "468",
        "287"
      ],
      "Output": "109278\n41041\n"
    },
    {
      "Input": [
        "4",
        "613",
        "155"
      ],
      "Output": "187578\n11935\n"
    },
    {
      "Input": [
        "4",
        "473",
        "162"
      ],
      "Output": "111628\n13041\n"
    },
    {
      "Input": [
        "4",
        "852",
        "75"
      ],
      "Output": "362526\n2775\n"
    },
    {
      "Input": [
        "4",
        "147",
        "33"
      ],
      "Output": "10731\n528\n"
    },
    {
      "Input": [
        "4",
        "984",
        "119"
      ],
      "Output": "483636\n7021\n"
    },
    {
      "Input": [
        "4",
        "312",
        "256"
      ],
      "Output": "48516\n32640\n"
    },
    {
      "Input": [
        "4",
        "241",
        "192"
      ],
      "Output": "28920\n18336\n"
    },
    {
      "Input": [
        "4",
        "452",
        "945"
      ],
      "Output": "101926\n446040\n"
    },
    {
      "Input": [
        "4",
        "816",
        "873"
      ],
      "Output": "332520\n380628\n"
    },
    {
      "Input": [
        "4",
        "180",
        "56"
      ],
      "Output": "16110\n1540\n"
    },
    {
      "Input": [
        "4",
        "784",
        "523"
      ],
      "Output": "306936\n136503\n"
    },
    {
      "Input": [
        "4",
        "621",
        "632"
      ],
      "Output": "192510\n199396\n"
    },
    {
      "Input": [
        "4",
        "998",
        "404"
      ],
      "Output": "497503\n81406\n"
    },
    {
      "Input": [
        "4",
        "713",
        "514"
      ],
      "Output": "253828\n131841\n"
    },
    {
      "Input": [
        "4",
        "419",
        "15"
      ],
      "Output": "87571\n105\n"
    },
    {
      "Input": [
        "4",
        "870",
        "697"
      ],
      "Output": "378015\n242556\n"
    },
    {
      "Input": [
        "4",
        "532",
        "987"
      ],
      "Output": "141246\n486591\n"
    },
    {
      "Input": [
        "4",
        "342",
        "360"
      ],
      "Output": "58311\n64620\n"
    },
    {
      "Input": [
        "4",
        "641",
        "370"
      ],
      "Output": "205120\n68265\n"
    },
    {
      "Input": [
        "4",
        "433",
        "941"
      ],
      "Output": "93528\n442270\n"
    },
    {
      "Input": [
        "4",
        "998",
        "656"
      ],
      "Output": "497503\n214840\n"
    },
    {
      "Input": [
        "4",
        "211",
        "147"
      ],
      "Output": "22155\n10731\n"
    },
    {
      "Input": [
        "4",
        "567",
        "10"
      ],
      "Output": "160461\n45\n"
    },
    {
      "Input": [
        "4",
        "541",
        "506"
      ],
      "Output": "146070\n127765\n"
    },
    {
      "Input": [
        "4",
        "385",
        "745"
      ],
      "Output": "73920\n277140\n"
    },
    {
      "Input": [
        "4",
        "952",
        "518"
      ],
      "Output": "452676\n133903\n"
    },
    {
      "Input": [
        "4",
        "17",
        "832"
      ],
      "Output": "136\n345696\n"
    },
    {
      "Input": [
        "4",
        "224",
        "436"
      ],
      "Output": "24976\n94830\n"
    },
    {
      "Input": [
        "4",
        "119",
        "980"
      ],
      "Output": "7021\n479710\n"
    },
    {
      "Input": [
        "4",
        "560",
        "644"
      ],
      "Output": "156520\n207046\n"
    },
    {
      "Input": [
        "4",
        "947",
        "454"
      ],
      "Output": "447931\n102831\n"
    },
    {
      "Input": [
        "4",
        "695",
        "930"
      ],
      "Output": "241165\n431985\n"
    },
    {
      "Input": [
        "4",
        "841",
        "201"
      ],
      "Output": "353220\n20100\n"
    },
    {
      "Input": [
        "4",
        "513",
        "480"
      ],
      "Output": "131328\n114960\n"
    },
    {
      "Input": [
        "4",
        "943",
        "249"
      ],
      "Output": "444153\n30876\n"
    },
    {
      "Input": [
        "4",
        "462",
        "86"
      ],
      "Output": "106491\n3655\n"
    },
    {
      "Input": [
        "4",
        "326",
        "31"
      ],
      "Output": "52975\n465\n"
    },
    {
      "Input": [
        "4",
        "123",
        "483"
      ],
      "Output": "7503\n116403\n"
    },
    {
      "Input": [
        "4",
        "587",
        "409"
      ],
      "Output": "171991\n83436\n"
    },
    {
      "Input": [
        "4",
        "721",
        "791"
      ],
      "Output": "259560\n312445\n"
    },
    {
      "Input": [
        "4",
        "881",
        "697"
      ],
      "Output": "387640\n242556\n"
    },
    {
      "Input": [
        "4",
        "382",
        "84"
      ],
      "Output": "72771\n3486\n"
    },
    {
      "Input": [
        "4",
        "937",
        "844"
      ],
      "Output": "438516\n355746\n"
    },
    {
      "Input": [
        "4",
        "822",
        "134"
      ],
      "Output": "337431\n8911\n"
    },
    {
      "Input": [
        "4",
        "687",
        "464"
      ],
      "Output": "235641\n107416\n"
    },
    {
      "Input": [
        "4",
        "737",
        "776"
      ],
      "Output": "271216\n300700\n"
    },
    {
      "Input": [
        "4",
        "837",
        "811"
      ],
      "Output": "349866\n328455\n"
    },
    {
      "Input": [
        "4",
        "721",
        "354"
      ],
      "Output": "259560\n62481\n"
    },
    {
      "Input": [
        "4",
        "73",
        "200"
      ],
      "Output": "2628\n19900\n"
    },
    {
      "Input": [
        "4",
        "694",
        "771"
      ],
      "Output": "240471\n296835\n"
    },
    {
      "Input": [
        "4",
        "343",
        "431"
      ],
      "Output": "58653\n92665\n"
    },
    {
      "Input": [
        "4",
        "113",
        "442"
      ],
      "Output": "6328\n97461\n"
    },
    {
      "Input": [
        "4",
        "890",
        "191"
      ],
      "Output": "395605\n18145\n"
    },
    {
      "Input": [
        "4",
        "642",
        "770"
      ],
      "Output": "205761\n296065\n"
    },
    {
      "Input": [
        "4",
        "54",
        "641"
      ],
      "Output": "1431\n205120\n"
    },
    {
      "Input": [
        "4",
        "477",
        "159"
      ],
      "Output": "113526\n12561\n"
    },
    {
      "Input": [
        "4",
        "218",
        "715"
      ],
      "Output": "23653\n255255\n"
    },
    {
      "Input": [
        "4",
        "676",
        "284"
      ],
      "Output": "228150\n40186\n"
    },
    {
      "Input": [
        "4",
        "198",
        "480"
      ],
      "Output": "19503\n114960\n"
    },
    {
      "Input": [
        "4",
        "55",
        "642"
      ],
      "Output": "1485\n205761\n"
    },
    {
      "Input": [
        "4",
        "709",
        "101"
      ],
      "Output": "250986\n5050\n"
    },
    {
      "Input": [
        "4",
        "855",
        "346"
      ],
      "Output": "365085\n59685\n"
    },
    {
      "Input": [
        "4",
        "237",
        "480"
      ],
      "Output": "27966\n114960\n"
    },
    {
      "Input": [
        "4",
        "789",
        "265"
      ],
      "Output": "310866\n34980\n"
    },
    {
      "Input": [
        "4",
        "434",
        "745"
      ],
      "Output": "93961\n277140\n"
    },
    {
      "Input": [
        "4",
        "574",
        "294"
      ],
      "Output": "164451\n43071\n"
    },
    {
      "Input": [
        "4",
        "246",
        "435"
      ],
      "Output": "30135\n94395\n"
    },
    {
      "Input": [
        "4",
        "660",
        "948"
      ],
      "Output": "217470\n448878\n"
    },
    {
      "Input": [
        "4",
        "413",
        "675"
      ],
      "Output": "85078\n227475\n"
    },
    {
      "Input": [
        "4",
        "810",
        "790"
      ],
      "Output": "327645\n311655\n"
    },
    {
      "Input": [
        "4",
        "765",
        "657"
      ],
      "Output": "292230\n215496\n"
    },
    {
      "Input": [
        "4",
        "520",
        "735"
      ],
      "Output": "134940\n269745\n"
    },
    {
      "Input": [
        "4",
        "623",
        "979"
      ],
      "Output": "193753\n478731\n"
    },
    {
      "Input": [
        "4",
        "920",
        "159"
      ],
      "Output": "422740\n12561\n"
    },
    {
      "Input": [
        "4",
        "240",
        "16"
      ],
      "Output": "28680\n120\n"
    },
    {
      "Input": [
        "4",
        "568",
        "303"
      ],
      "Output": "161028\n45753\n"
    },
    {
      "Input": [
        "4",
        "965",
        "311"
      ],
      "Output": "465130\n48205\n"
    },
    {
      "Input": [
        "4",
        "471",
        "571"
      ],
      "Output": "110685\n162735\n"
    },
    {
      "Input": [
        "4",
        "963",
        "933"
      ],
      "Output": "463203\n434778\n"
    },
    {
      "Input": [
        "4",
        "871",
        "816"
      ],
      "Output": "378885\n332520\n"
    },
    {
      "Input": [
        "4",
        "24",
        "346"
      ],
      "Output": "276\n59685\n"
    },
    {
      "Input": [
        "4",
        "485",
        "275"
      ],
      "Output": "117370\n37675\n"
    },
    {
      "Input": [
        "4",
        "468",
        "870"
      ],
      "Output": "109278\n378015\n"
    },
    {
      "Input": [
        "4",
        "648",
        "26"
      ],
      "Output": "209628\n325\n"
    },
    {
      "Input": [
        "4",
        "250",
        "369"
      ],
      "Output": "31125\n67896\n"
    },
    {
      "Input": [
        "4",
        "163",
        "608"
      ],
      "Output": "13203\n184528\n"
    },
    {
      "Input": [
        "4",
        "194",
        "805"
      ],
      "Output": "18721\n323610\n"
    },
    {
      "Input": [
        "4",
        "674",
        "96"
      ],
      "Output": "226801\n4560\n"
    },
    {
      "Input": [
        "4",
        "122",
        "401"
      ],
      "Output": "7381\n80200\n"
    },
    {
      "Input": [
        "4",
        "316",
        "740"
      ],
      "Output": "49770\n273430\n"
    },
    {
      "Input": [
        "4",
        "194",
        "743"
      ],
      "Output": "18721\n275653\n"
    },
    {
      "Input": [
        "4",
        "334",
        "982"
      ],
      "Output": "55611\n481671\n"
    },
    {
      "Input": [
        "4",
        "991",
        "65"
      ],
      "Output": "490545\n2080\n"
    },
    {
      "Input": [
        "4",
        "657",
        "803"
      ],
      "Output": "215496\n322003\n"
    },
    {
      "Input": [
        "4",
        "23",
        "202"
      ],
      "Output": "253\n20301\n"
    },
    {
      "Input": [
        "4",
        "30",
        "240"
      ],
      "Output": "435\n28680\n"
    },
    {
      "Input": [
        "4",
        "551",
        "568"
      ],
      "Output": "151525\n161028\n"
    },
    {
      "Input": [
        "4",
        "565",
        "631"
      ],
      "Output": "159330\n198765\n"
    },
    {
      "Input": [
        "4",
        "144",
        "333"
      ],
      "Output": "10296\n55278\n"
    },
    {
      "Input": [
        "4",
        "136",
        "160"
      ],
      "Output": "9180\n12720\n"
    },
    {
      "Input": [
        "4",
        "332",
        "743"
      ],
      "Output": "54946\n275653\n"
    },
    {
      "Input": [
        "4",
        "247",
        "598"
      ],
      "Output": "30381\n178503\n"
    },
    {
      "Input": [
        "4",
        "124",
        "333"
      ],
      "Output": "7626\n55278\n"
    },
    {
      "Input": [
        "4",
        "368",
        "216"
      ],
      "Output": "67528\n23220\n"
    },
    {
      "Input": [
        "4",
        "14",
        "282"
      ],
      "Output": "91\n39621\n"
    },
    {
      "Input": [
        "4",
        "587",
        "420"
      ],
      "Output": "171991\n87990\n"
    },
    {
      "Input": [
        "4",
        "968",
        "786"
      ],
      "Output": "468028\n308505\n"
    },
    {
      "Input": [
        "4",
        "897",
        "261"
      ],
      "Output": "401856\n33930\n"
    },
    {
      "Input": [
        "4",
        "256",
        "83"
      ],
      "Output": "32640\n3403\n"
    },
    {
      "Input": [
        "4",
        "250",
        "793"
      ],
      "Output": "31125\n314028\n"
    },
    {
      "Input": [
        "4",
        "662",
        "752"
      ],
      "Output": "218791\n282376\n"
    },
    {
      "Input": [
        "4",
        "148",
        "752"
      ],
      "Output": "10878\n282376\n"
    },
    {
      "Input": [
        "4",
        "931",
        "4"
      ],
      "Output": "432915\n6\n"
    },
    {
      "Input": [
        "4",
        "572",
        "149"
      ],
      "Output": "163306\n11026\n"
    },
    {
      "Input": [
        "4",
        "67",
        "163"
      ],
      "Output": "2211\n13203\n"
    },
    {
      "Input": [
        "4",
        "177",
        "465"
      ],
      "Output": "15576\n107880\n"
    },
    {
      "Input": [
        "4",
        "784",
        "643"
      ],
      "Output": "306936\n206403\n"
    },
    {
      "Input": [
        "4",
        "766",
        "630"
      ],
      "Output": "292995\n198135\n"
    },
    {
      "Input": [
        "4",
        "871",
        "996"
      ],
      "Output": "378885\n495510\n"
    },
    {
      "Input": [
        "4",
        "968",
        "62"
      ],
      "Output": "468028\n1891\n"
    },
    {
      "Input": [
        "4",
        "995",
        "728"
      ],
      "Output": "494515\n264628\n"
    },
    {
      "Input": [
        "4",
        "980",
        "560"
      ],
      "Output": "479710\n156520\n"
    },
    {
      "Input": [
        "4",
        "703",
        "245"
      ],
      "Output": "246753\n29890\n"
    },
    {
      "Input": [
        "4",
        "699",
        "333"
      ],
      "Output": "243951\n55278\n"
    },
    {
      "Input": [
        "4",
        "184",
        "30"
      ],
      "Output": "16836\n435\n"
    },
    {
      "Input": [
        "4",
        "530",
        "816"
      ],
      "Output": "140185\n332520\n"
    },
    {
      "Input": [
        "4",
        "702",
        "361"
      ],
      "Output": "246051\n64980\n"
    },
    {
      "Input": [
        "4",
        "26",
        "813"
      ],
      "Output": "325\n330078\n"
    },
    {
      "Input": [
        "4",
        "345",
        "950"
      ],
      "Output": "59340\n450775\n"
    },
    {
      "Input": [
        "4",
        "355",
        "2"
      ],
      "Output": "62835\n1\n"
    },
    {
      "Input": [
        "4",
        "299",
        "267"
      ],
      "Output": "44551\n35511\n"
    },
    {
      "Input": [
        "4",
        "286",
        "767"
      ],
      "Output": "40755\n293761\n"
    },
    {
      "Input": [
        "4",
        "81",
        "953"
      ],
      "Output": "3240\n453628\n"
    },
    {
      "Input": [
        "4",
        "441",
        "328"
      ],
      "Output": "97020\n53628\n"
    },
    {
      "Input": [
        "4",
        "24",
        "881"
      ],
      "Output": "276\n387640\n"
    },
    {
      "Input": [
        "4",
        "187",
        "522"
      ],
      "Output": "17391\n135981\n"
    },
    {
      "Input": [
        "4",
        "728",
        "488"
      ],
      "Output": "264628\n118828\n"
    },
    {
      "Input": [
        "4",
        "673",
        "242"
      ],
      "Output": "226128\n29161\n"
    },
    {
      "Input": [
        "4",
        "222",
        "84"
      ],
      "Output": "24531\n3486\n"
    },
    {
      "Input": [
        "4",
        "834",
        "512"
      ],
      "Output": "347361\n130816\n"
    },
    {
      "Input": [
        "4",
        "257",
        "684"
      ],
      "Output": "32896\n233586\n"
    },
    {
      "Input": [
        "4",
        "446",
        "197"
      ],
      "Output": "99235\n19306\n"
    },
    {
      "Input": [
        "4",
        "800",
        "938"
      ],
      "Output": "319600\n439453\n"
    },
    {
      "Input": [
        "4",
        "153",
        "204"
      ],
      "Output": "11628\n20706\n"
    },
    {
      "Input": [
        "4",
        "501",
        "366"
      ],
      "Output": "125250\n66795\n"
    },
    {
      "Input": [
        "4",
        "579",
        "442"
      ],
      "Output": "167331\n97461\n"
    },
    {
      "Input": [
        "4",
        "864",
        "48"
      ],
      "Output": "372816\n1128\n"
    },
    {
      "Input": [
        "4",
        "132",
        "139"
      ],
      "Output": "8646\n9591\n"
    },
    {
      "Input": [
        "4",
        "897",
        "8"
      ],
      "Output": "401856\n28\n"
    },
    {
      "Input": [
        "4",
        "331",
        "476"
      ],
      "Output": "54615\n113050\n"
    },
    {
      "Input": [
        "4",
        "563",
        "313"
      ],
      "Output": "158203\n48828\n"
    },
    {
      "Input": [
        "4",
        "325",
        "351"
      ],
      "Output": "52650\n61425\n"
    },
    {
      "Input": [
        "4",
        "203",
        "447"
      ],
      "Output": "20503\n99681\n"
    },
    {
      "Input": [
        "4",
        "453",
        "196"
      ],
      "Output": "102378\n19110\n"
    },
    {
      "Input": [
        "4",
        "816",
        "270"
      ],
      "Output": "332520\n36315\n"
    },
    {
      "Input": [
        "4",
        "688",
        "558"
      ],
      "Output": "236328\n155403\n"
    },
    {
      "Input": [
        "4",
        "378",
        "29"
      ],
      "Output": "71253\n406\n"
    },
    {
      "Input": [
        "4",
        "118",
        "2"
      ],
      "Output": "6903\n1\n"
    },
    {
      "Input": [
        "4",
        "234",
        "819"
      ],
      "Output": "27261\n334971\n"
    },
    {
      "Input": [
        "4",
        "536",
        "689"
      ],
      "Output": "143380\n237016\n"
    },
    {
      "Input": [
        "4",
        "128",
        "943"
      ],
      "Output": "8128\n444153\n"
    },
    {
      "Input": [
        "4",
        "116",
        "426"
      ],
      "Output": "6670\n90525\n"
    },
    {
      "Input": [
        "4",
        "966",
        "913"
      ],
      "Output": "466095\n416328\n"
    },
    {
      "Input": [
        "4",
        "120",
        "153"
      ],
      "Output": "7140\n11628\n"
    },
    {
      "Input": [
        "4",
        "141",
        "216"
      ],
      "Output": "9870\n23220\n"
    },
    {
      "Input": [
        "4",
        "640",
        "634"
      ],
      "Output": "204480\n200661\n"
    },
    {
      "Input": [
        "4",
        "25",
        "588"
      ],
      "Output": "300\n172578\n"
    },
    {
      "Input": [
        "4",
        "511",
        "282"
      ],
      "Output": "130305\n39621\n"
    }
  ]
}